SnmpLibrary/__init__.py
SnmpLibrary/library.py
SnmpLibrary/traps.py
SnmpLibrary/utils.py
SnmpLibrary/version.py
robotframework_snmplibrary-0.2.2.dist-info/AUTHORS
robotframework_snmplibrary-0.2.2.dist-info/COPYING
robotframework_snmplibrary-0.2.2.dist-info/METADATA
robotframework_snmplibrary-0.2.2.dist-info/WHEEL
robotframework_snmplibrary-0.2.2.dist-info/top_level.txt
robotframework_snmplibrary-0.2.2.dist-info/RECORD
