Metadata-Version: 2.1
Name: robotframework-snmplibrary
Version: 0.2.2
Summary: SNMP Library for Robot Framework
Home-page: https://github.com/kontron/robotframework-snmplibrary
Download-URL: https://pypi.python.org/pypi/robotframework-snmplibrary
Author: Michael Walle
Author-email: michael.walle@kontron.com
License: Apache License 2.0
Classifier: Development Status :: 4 - Beta
Classifier: Framework :: Robot Framework
Classifier: License :: OSI Approved :: Apache Software License
Classifier: Operating System :: OS Independent
Classifier: Programming Language :: Python :: 2
Classifier: Programming Language :: Python :: 2.7
Classifier: Programming Language :: Python :: 3
Classifier: Programming Language :: Python :: 3.4
Classifier: Programming Language :: Python :: 3.5
Classifier: Programming Language :: Python :: 3.6
Classifier: Topic :: Software Development :: Testing
License-File: COPYING
License-File: AUTHORS
Requires-Dist: robotframework
Requires-Dist: pysnmp
